{
  "main": {
    "id": "42eaa7a6ca860bbd",
    "type": "split",
    "children": [
      {
        "id": "b637ed5441f81915",
        "type": "tabs",
        "children": [
          {
            "id": "849d8e9685bab00f",
            "type": "leaf",
            "state": {
              "type": "markdown",
              "state": {
                "file": "Templates/try.md",
                "mode": "source",
                "source": false
              },
              "icon": "lucide-file",
              "title": "try"
            }
          }
        ]
      }
    ],
    "direction": "vertical"
  },
  "left": {
    "id": "68c5099ef41a9c5b",
    "type": "split",
    "children": [
      {
        "id": "ce593578c9128962",
        "type": "tabs",
        "children": [
          {
            "id": "23a6f7fceccea430",
            "type": "leaf",
            "state": {
              "type": "file-explorer",
              "state": {
                "sortOrder": "alphabetical",
                "autoReveal": true
              },
              "icon": "lucide-folder-closed",
              "title": "파일 탐색기"
            }
          },
          {
            "id": "d4012a825ff61b8a",
            "type": "leaf",
            "state": {
              "type": "search",
              "state": {
                "query": "",
                "matchingCase": false,
                "explainSearch": false,
                "collapseAll": false,
                "extraContext": false,
                "sortOrder": "alphabetical"
              },
              "icon": "lucide-search",
              "title": "검색"
            }
          },
          {
            "id": "e45a0a4a53f3ef38",
            "type": "leaf",
            "state": {
              "type": "bookmarks",
              "state": {},
              "icon": "lucide-bookmark",
              "title": "북마크"
            }
          }
        ]
      }
    ],
    "direction": "horizontal",
    "width": 300
  },
  "right": {
    "id": "96a1f7055ca490f8",
    "type": "split",
    "children": [
      {
        "id": "681603351cb58243",
        "type": "tabs",
        "children": [
          {
            "id": "1612973a0cb7d4dc",
            "type": "leaf",
            "state": {
              "type": "backlink",
              "state": {
                "file": "Templates/try.md",
                "collapseAll": false,
                "extraContext": false,
                "sortOrder": "alphabetical",
                "showSearch": false,
                "searchQuery": "",
                "backlinkCollapsed": false,
                "unlinkedCollapsed": true
              },
              "icon": "links-coming-in",
              "title": "try 의 백링크"
            }
          },
          {
            "id": "0e7cdf71fdfeddec",
            "type": "leaf",
            "state": {
              "type": "outgoing-link",
              "state": {
                "file": "Templates/try.md",
                "linksCollapsed": false,
                "unlinkedCollapsed": true
              },
              "icon": "links-going-out",
              "title": "try 의 나가는 링크"
            }
          },
          {
            "id": "b2e01cfdc7e30da5",
            "type": "leaf",
            "state": {
              "type": "tag",
              "state": {
                "sortOrder": "frequency",
                "useHierarchy": true,
                "showSearch": false,
                "searchQuery": ""
              },
              "icon": "lucide-tags",
              "title": "태그"
            }
          },
          {
            "id": "caad74805042501a",
            "type": "leaf",
            "state": {
              "type": "outline",
              "state": {
                "file": "Templates/try.md",
                "followCursor": false,
                "showSearch": false,
                "searchQuery": ""
              },
              "icon": "lucide-list",
              "title": "try 의 개요"
            }
          },
          {
            "id": "929aa180fd35c51e",
            "type": "leaf",
            "state": {
              "type": "git-view",
              "state": {},
              "icon": "git-pull-request",
              "title": "Source Control"
            }
          }
        ],
        "currentTab": 4
      }
    ],
    "direction": "horizontal",
    "width": 300
  },
  "left-ribbon": {
    "hiddenItems": {
      "switcher:빠른 전환기 열기": false,
      "graph:그래프 뷰 열기": false,
      "canvas:새 캔버스 만들기": false,
      "daily-notes:오늘의 일일 노트 열기": false,
      "templates:템플릿 삽입": false,
      "command-palette:명령어 팔레트 열기": false,
      "obsidian-git:Open Git source control": false
    }
  },
  "active": "849d8e9685bab00f",
  "lastOpenFiles": [
    "Templates/try.md",
    "2025-05-11.md",
    "README.md",
    "Docs/정규식 DSL.md",
    "Docs/프로토콜 지향 프로그래밍 (POP).md",
    "Templates/Template.md",
    "Welcome.md",
    "첫 메모.md",
    "Untitled 1.canvas",
    "Untitled.canvas",
    "Docs/LLVM 컴파일러.md",
    "Docs/Swift.md",
    "Docs/Swift Standard Library.md",
    "Docs/데이터 모델링 (Data Modeling).md",
    "Docs/병렬 처리(Swift-Concurrency).md",
    "Docs/열거형 (Enumeration).md",
    "Templates",
    "Docs/클로저 (Closure).md",
    "Docs/제네릭 (Generic).md",
    "Docs/옵셔널(Optionals).md",
    "Docs",
    "2025-05-10.md",
    "옵시디언/옵시디언.md",
    "옵시디언"
  ]
}